editor_texto_tk/__init__.py
mensajes2/__init__.py
mensajes2/adios/__init__.py
mensajes2/adios/despedidas.py
mensajes2/saludos/__init__.py
mensajes2/saludos/saludos.py
mensajes2/saludos/saludos_mod_externo.py
saludo_tk/__init__.py
tests/__init__.py
tests/test_adios.py
tests/test_saludos.py
Mensajes_AlexisNieto.Coder-6.0.dist-info/LICENSE
Mensajes_AlexisNieto.Coder-6.0.dist-info/METADATA
Mensajes_AlexisNieto.Coder-6.0.dist-info/WHEEL
Mensajes_AlexisNieto.Coder-6.0.dist-info/top_level.txt
Mensajes_AlexisNieto.Coder-6.0.dist-info/RECORD
