Metadata-Version: 2.1
Name: Mensajes-AlexisNieto.Coder
Version: 6.0
Summary: Un Paquete Para Saludar Y Despedir
Home-page: https://github.com/Aleont18/.git
Author: Alexis Nieto
Author-email: alexisnieto.coder@gmail.com
Classifier: Environment :: Console
Classifier: Intended Audience :: Developers
Classifier: License :: OSI Approved :: MIT License
Classifier: Operating System :: OS Independent
Classifier: Programming Language :: Python
Classifier: Topic :: Utilities
License-File: LICENSE
Requires-Dist: numpy >=1.26.0
